ascii_gradient_art/ascii_gradient_art.py
ascii_gradient_art/main.py
ascii_gradient_art/setup.py
ascii_gradient_art/core/__init__.py
ascii_gradient_art/core/color_utils.py
ascii_gradient_art/core/generator.py
ascii_gradient_art/themes/__init__.py
ascii_gradient_art/themes/default_themes.py
ascii_gradient_art/utils/__init__.py
ascii_gradient_art/utils/cli_parser.py
ascii_gradient_art-0.1.5.dist-info/licenses/LICENSE
ascii_gradient_art-0.1.5.dist-info/METADATA
ascii_gradient_art-0.1.5.dist-info/WHEEL
ascii_gradient_art-0.1.5.dist-info/entry_points.txt
ascii_gradient_art-0.1.5.dist-info/top_level.txt
ascii_gradient_art-0.1.5.dist-info/RECORD
