Metadata-Version: 2.4
Name: ascii-gradient-art
Version: 0.1.5
Summary: A command-line tool to generate colorful ASCII art with gradients and animations.
Author: Maxzs
Maintainer: Maxzs
License: MIT
Project-URL: Homepage, https://github.com/crazyZSShuo/ascii-gradient-art
Project-URL: Repository, https://github.com/crazyZSShuo/ascii-gradient-art
Project-URL: Source Code, https://github.com/crazyZSShuo/ascii-gradient-art
Project-URL: Bug Tracker, https://github.com/crazyZSShuo/ascii-gradient-art/issues
Project-URL: Documentation, https://github.com/crazyZSShuo/ascii-gradient-art#readme
Project-URL: Download, https://pypi.org/project/ascii-gradient-art/
Keywords: ascii,art,gradient,color,animation,terminal,cli
Classifier: Programming Language :: Python :: 3
Classifier: License :: OSI Approved :: MIT License
Classifier: Operating System :: OS Independent
Classifier: Environment :: Console
Classifier: Development Status :: 4 - Beta
Classifier: Intended Audience :: Developers
Classifier: Intended Audience :: End Users/Desktop
Classifier: Topic :: Artistic Software
Classifier: Topic :: Multimedia :: Graphics
Classifier: Topic :: Terminals
Classifier: Topic :: Utilities
Requires-Python: >=3.6
License-File: LICENSE
Requires-Dist: pyfiglet
Dynamic: license-file
